README.rst
setup.py
jsre/__init__.py
jsre/charclass.py
jsre/dfacompiler.py
jsre/header.py
jsre/recompiler.py
jsre/reobjects.py
jsre/reparser.py
jsre/test.py
jsre/tools.py
jsre/ucd.py
jsre.egg-info/PKG-INFO
jsre.egg-info/SOURCES.txt
jsre.egg-info/dependency_links.txt
jsre.egg-info/top_level.txt
jsre/JSRE_Compiled/compile.log
jsre/JSRE_Compiled/ascii/alnum
jsre/JSRE_Compiled/ascii/alphabetic
jsre/JSRE_Compiled/ascii/any
jsre/JSRE_Compiled/ascii/ascii
jsre/JSRE_Compiled/ascii/ascii_hex_digit
jsre/JSRE_Compiled/ascii/assigned
jsre/JSRE_Compiled/ascii/blank
jsre/JSRE_Compiled/ascii/case_ignorable
jsre/JSRE_Compiled/ascii/cased
jsre/JSRE_Compiled/ascii/changes_when_casefolded
jsre/JSRE_Compiled/ascii/changes_when_casemapped
jsre/JSRE_Compiled/ascii/changes_when_lowercased
jsre/JSRE_Compiled/ascii/changes_when_titlecased
jsre/JSRE_Compiled/ascii/changes_when_uppercased
jsre/JSRE_Compiled/ascii/crlf
jsre/JSRE_Compiled/ascii/dash
jsre/JSRE_Compiled/ascii/diacritic
jsre/JSRE_Compiled/ascii/dot_any
jsre/JSRE_Compiled/ascii/graph
jsre/JSRE_Compiled/ascii/grapheme_base
jsre/JSRE_Compiled/ascii/hex_digit
jsre/JSRE_Compiled/ascii/hyphen
jsre/JSRE_Compiled/ascii/id_continue
jsre/JSRE_Compiled/ascii/id_start
jsre/JSRE_Compiled/ascii/lowercase
jsre/JSRE_Compiled/ascii/math
jsre/JSRE_Compiled/ascii/newline
jsre/JSRE_Compiled/ascii/not_blank
jsre/JSRE_Compiled/ascii/not_digit
jsre/JSRE_Compiled/ascii/not_word
jsre/JSRE_Compiled/ascii/other_math
jsre/JSRE_Compiled/ascii/pattern_syntax
jsre/JSRE_Compiled/ascii/pattern_white_space
jsre/JSRE_Compiled/ascii/print
jsre/JSRE_Compiled/ascii/quotation_mark
jsre/JSRE_Compiled/ascii/soft_dotted
jsre/JSRE_Compiled/ascii/sterm
jsre/JSRE_Compiled/ascii/terminal_punctuation
jsre/JSRE_Compiled/ascii/uppercase
jsre/JSRE_Compiled/ascii/white_space
jsre/JSRE_Compiled/ascii/word
jsre/JSRE_Compiled/ascii/xdigit
jsre/JSRE_Compiled/ascii/xid_continue
jsre/JSRE_Compiled/ascii/xid_start
jsre/JSRE_Compiled/ascii/general_category/cased_letter
jsre/JSRE_Compiled/ascii/general_category/close_punctuation
jsre/JSRE_Compiled/ascii/general_category/connector_punctuation
