Metadata-Version: 1.1
Name: jsre
Version: 1.1.1
Summary: Regular expression module for forensics and big data
Home-page: UNKNOWN
Author: Howard Chivers
Author-email: howard.chivers@york.ac.uk
License: BSD New
Keywords: regular expressions search forensic
Platform: UNKNOWN
Classifier: Development Status :: 4 - Beta
Classifier: Intended Audience :: Science/Research
Classifier: License :: OSI Approved :: BSD License
Classifier: Operating System :: OS Independent
Classifier: Programming Language :: Python :: 3
Classifier: Topic :: Scientific/Engineering :: Information Analysis
Classifier: Topic :: Software Development :: Libraries :: Python Modules
Classifier: Topic :: Text Processing :: General
